pycalbuddy/__init__.py
pycalbuddy/applescript.py
pycalbuddy/cli.py
pycalbuddy/eventkit.py
pycalbuddy/icalbuddy.py
pycalbuddy/models.py
pycalbuddy/service.py
pycalbuddy-0.1.5.dist-info/METADATA
pycalbuddy-0.1.5.dist-info/WHEEL
pycalbuddy-0.1.5.dist-info/entry_points.txt
pycalbuddy-0.1.5.dist-info/licenses/LICENSE
pycalbuddy-0.1.5.dist-info/RECORD
