Metadata-Version: 2.4
Name: pycalbuddy
Version: 0.1.5
Summary: Thin EventKit wrapper for macOS Calendar access.
Author: Artem Veremey
License: MIT
License-File: LICENSE
Requires-Python: >=3.11
Requires-Dist: pyobjc-framework-eventkit; platform_system == 'Darwin'
